<?xml version="1.0" encoding="utf-8"?>
<smsf xmlns="smsf2">
  <pdc>
    <name>OH2_RJ_FURNAS_50fps_041125_v3</name>
    <type>openpdc</type>
    <fps>50</fps>
    <address>192.168.254.21:6156</address>
    <security>
      <user></user>
      <pswd></pswd>
    </security>
  </pdc>
  <pmu>
    <idName>CV STF6 500 P1 TR1 VAO</idName>
    <fullName>CV STF6 500 P1 TR1 VAO</fullName>
    <voltLevel>500000</voltLevel>
    <local>
      <area>S</area>
      <state>PR</state>
      <station>Foz do Iguaçu</station>
      <lat>-25.471197</lat>
      <lon>-54.549554</lon>
    </local>
    <measurements>
      <phasor>
        <pName>TENSAO_A</pName>
        <pType>Voltage</pType>
        <pPhase>A</pPhase>
        <modId>20217</modId>
        <angId>20218</angId>
      </phasor>
      <phasor>
        <pName>TENSAO_B</pName>
        <pType>Voltage</pType>
        <pPhase>B</pPhase>
        <modId>20215</modId>
        <angId>20216</angId>
      </phasor>
      <phasor>
        <pName>TENSAO_C</pName>
        <pType>Voltage</pType>
        <pPhase>C</pPhase>
        <modId>20213</modId>
        <angId>20214</angId>
      </phasor>
      <phasor>
        <pName>CORRENTE_A</pName>
        <pType>Current</pType>
        <pPhase>A</pPhase>
        <modId>20223</modId>
        <angId>20224</angId>
      </phasor>
      <phasor>
        <pName>CORRENTE_B</pName>
        <pType>Current</pType>
        <pPhase>B</pPhase>
        <modId>20221</modId>
        <angId>20222</angId>
      </phasor>
      <phasor>
        <pName>CORRENTE_C</pName>
        <pType>Current</pType>
        <pPhase>C</pPhase>
        <modId>20219</modId>
        <angId>20220</angId>
      </phasor>
      <freq>
        <fName>FREQUENCIA</fName>
        <fId>20210</fId>
      </freq>
      <dFreq>
        <dfName>DFREQ</dfName>
        <dfId>20211</dfId>
      </dFreq>
    </measurements>
  </pmu>
  <pmu>
    <idName>CV STF6 500 P1 TR3 VAO</idName>
    <fullName>CV STF6 500 P1 TR3 VAO</fullName>
    <voltLevel>500000</voltLevel>
    <local>
      <area>S</area>
      <state>PR</state>
      <station>Foz do Iguaçu</station>
      <lat>-25.471197</lat>
      <lon>-54.549554</lon>
    </local>
    <measurements>
      <phasor>
        <pName>TENSAO_A</pName>
        <pType>Voltage</pType>
        <pPhase>A</pPhase>
        <modId>20319</modId>
        <angId>20320</angId>
      </phasor>
      <phasor>
        <pName>TENSAO_B</pName>
        <pType>Voltage</pType>
        <pPhase>B</pPhase>
        <modId>20317</modId>
        <angId>20318</angId>
      </phasor>
      <phasor>
        <pName>TENSAO_C</pName>
        <pType>Voltage</pType>
        <pPhase>C</pPhase>
        <modId>20315</modId>
        <angId>20316</angId>
      </phasor>
      <phasor>
        <pName>CORRENTE_A</pName>
        <pType>Current</pType>
        <pPhase>A</pPhase>
        <modId>20325</modId>
        <angId>20326</angId>
      </phasor>
      <phasor>
        <pName>CORRENTE_B</pName>
        <pType>Current</pType>
        <pPhase>B</pPhase>
        <modId>20323</modId>
        <angId>20324</angId>
      </phasor>
      <phasor>
        <pName>CORRENTE_C</pName>
        <pType>Current</pType>
        <pPhase>C</pPhase>
        <modId>20321</modId>
        <angId>20322</angId>
      </phasor>
      <freq>
        <fName>FREQUENCIA</fName>
        <fId>20312</fId>
      </freq>
      <dFreq>
        <dfName>DFREQ</dfName>
        <dfId>20313</dfId>
      </dFreq>
    </measurements>
  </pmu>
  <pmu>
    <idName>CV STF6 500 P2 TR2 VAO</idName>
    <fullName>CV STF6 500 P2 TR2 VAO</fullName>
    <voltLevel>500000</voltLevel>
    <local>
      <area>S</area>
      <state>PR</state>
      <station>Foz do Iguaçu</station>
      <lat>-25.471197</lat>
      <lon>-54.549554</lon>
    </local>
    <measurements>
      <phasor>
        <pName>TENSAO_A</pName>
        <pType>Voltage</pType>
        <pPhase>A</pPhase>
        <modId>20421</modId>
        <angId>20422</angId>
      </phasor>
      <phasor>
        <pName>TENSAO_B</pName>
        <pType>Voltage</pType>
        <pPhase>B</pPhase>
        <modId>20419</modId>
        <angId>20420</angId>
      </phasor>
      <phasor>
        <pName>TENSAO_C</pName>
        <pType>Voltage</pType>
        <pPhase>C</pPhase>
        <modId>20417</modId>
        <angId>20418</angId>
      </phasor>
      <phasor>
        <pName>CORRENTE_A</pName>
        <pType>Current</pType>
        <pPhase>A</pPhase>
        <modId>20427</modId>
        <angId>20428</angId>
      </phasor>
      <phasor>
        <pName>CORRENTE_B</pName>
        <pType>Current</pType>
        <pPhase>B</pPhase>
        <modId>20425</modId>
        <angId>20426</angId>
      </phasor>
      <phasor>
        <pName>CORRENTE_C</pName>
        <pType>Current</pType>
        <pPhase>C</pPhase>
        <modId>20423</modId>
        <angId>20424</angId>
      </phasor>
      <freq>
        <fName>FREQUENCIA</fName>
        <fId>20414</fId>
      </freq>
      <dFreq>
        <dfName>DFREQ</dfName>
        <dfId>20415</dfId>
      </dFreq>
    </measurements>
  </pmu>
  <pmu>
    <idName>CV STF6 500 P2 TR4 VAO</idName>
    <fullName>CV STF6 500 P2 TR4 VAO</fullName>
    <voltLevel>500000</voltLevel>
    <local>
      <area>S</area>
      <state>PR</state>
      <station>Foz do Iguaçu</station>
      <lat>-25.471197</lat>
      <lon>-54.549554</lon>
    </local>
    <measurements>
      <phasor>
        <pName>TENSAO_A</pName>
        <pType>Voltage</pType>
        <pPhase>A</pPhase>
        <modId>20523</modId>
        <angId>20524</angId>
      </phasor>
      <phasor>
        <pName>TENSAO_B</pName>
        <pType>Voltage</pType>
        <pPhase>B</pPhase>
        <modId>20521</modId>
        <angId>20522</angId>
      </phasor>
      <phasor>
        <pName>TENSAO_C</pName>
        <pType>Voltage</pType>
        <pPhase>C</pPhase>
        <modId>20519</modId>
        <angId>20520</angId>
      </phasor>
      <phasor>
        <pName>CORRENTE_A</pName>
        <pType>Current</pType>
        <pPhase>A</pPhase>
        <modId>20529</modId>
        <angId>20530</angId>
      </phasor>
      <phasor>
        <pName>CORRENTE_B</pName>
        <pType>Current</pType>
        <pPhase>B</pPhase>
        <modId>20527</modId>
        <angId>20528</angId>
      </phasor>
      <phasor>
        <pName>CORRENTE_C</pName>
        <pType>Current</pType>
        <pPhase>C</pPhase>
        <modId>20525</modId>
        <angId>20526</angId>
      </phasor>
      <freq>
        <fName>FREQUENCIA</fName>
        <fId>20516</fId>
      </freq>
      <dFreq>
        <dfName>DFREQ</dfName>
        <dfId>20517</dfId>
      </dFreq>
    </measurements>
  </pmu>
  <pmu>
    <idName>CV STF6 500 P3 TR5 VAO</idName>
    <fullName>CV STF6 500 P3 TR5 VAO</fullName>
    <voltLevel>500000</voltLevel>
    <local>
      <area>S</area>
      <state>PR</state>
      <station>Foz do Iguaçu</station>
      <lat>-25.471197</lat>
      <lon>-54.549554</lon>
    </local>
    <measurements>
      <phasor>
        <pName>TENSAO_A</pName>
        <pType>Voltage</pType>
        <pPhase>A</pPhase>
        <modId>20625</modId>
        <angId>20626</angId>
      </phasor>
      <phasor>
        <pName>TENSAO_B</pName>
        <pType>Voltage</pType>
        <pPhase>B</pPhase>
        <modId>20623</modId>
        <angId>20624</angId>
      </phasor>
      <phasor>
        <pName>TENSAO_C</pName>
        <pType>Voltage</pType>
        <pPhase>C</pPhase>
        <modId>20621</modId>
        <angId>20622</angId>
      </phasor>
      <phasor>
        <pName>CORRENTE_A</pName>
        <pType>Current</pType>
        <pPhase>A</pPhase>
        <modId>20631</modId>
        <angId>20632</angId>
      </phasor>
      <phasor>
        <pName>CORRENTE_B</pName>
        <pType>Current</pType>
        <pPhase>B</pPhase>
        <modId>20629</modId>
        <angId>20630</angId>
      </phasor>
      <phasor>
        <pName>CORRENTE_C</pName>
        <pType>Current</pType>
        <pPhase>C</pPhase>
        <modId>20627</modId>
        <angId>20628</angId>
      </phasor>
      <freq>
        <fName>FREQUENCIA</fName>
        <fId>20618</fId>
      </freq>
      <dFreq>
        <dfName>DFREQ</dfName>
        <dfId>20619</dfId>
      </dFreq>
    </measurements>
  </pmu>
  <pmu>
    <idName>CV STF6 500 P3 TR7 VAO</idName>
    <fullName>CV STF6 500 P3 TR7 VAO</fullName>
    <voltLevel>500000</voltLevel>
    <local>
      <area>S</area>
      <state>PR</state>
      <station>Foz do Iguaçu</station>
      <lat>-25.471197</lat>
      <lon>-54.549554</lon>
    </local>
    <measurements>
      <phasor>
        <pName>TENSAO_A</pName>
        <pType>Voltage</pType>
        <pPhase>A</pPhase>
        <modId>20727</modId>
        <angId>20728</angId>
      </phasor>
      <phasor>
        <pName>TENSAO_B</pName>
        <pType>Voltage</pType>
        <pPhase>B</pPhase>
        <modId>20725</modId>
        <angId>20726</angId>
      </phasor>
      <phasor>
        <pName>TENSAO_C</pName>
        <pType>Voltage</pType>
        <pPhase>C</pPhase>
        <modId>20723</modId>
        <angId>20724</angId>
      </phasor>
      <phasor>
        <pName>CORRENTE_A</pName>
        <pType>Current</pType>
        <pPhase>A</pPhase>
        <modId>20733</modId>
        <angId>20734</angId>
      </phasor>
      <phasor>
        <pName>CORRENTE_B</pName>
        <pType>Current</pType>
        <pPhase>B</pPhase>
        <modId>20731</modId>
        <angId>20732</angId>
      </phasor>
      <phasor>
        <pName>CORRENTE_C</pName>
        <pType>Current</pType>
        <pPhase>C</pPhase>
        <modId>20729</modId>
        <angId>20730</angId>
      </phasor>
      <freq>
        <fName>FREQUENCIA</fName>
        <fId>20720</fId>
      </freq>
      <dFreq>
        <dfName>DFREQ</dfName>
        <dfId>20721</dfId>
      </dFreq>
    </measurements>
  </pmu>
  <pmu>
    <idName>CV STF6 500 P4 TR6 VAO</idName>
    <fullName>CV STF6 500 P4 TR6 VAO</fullName>
    <voltLevel>500000</voltLevel>
    <local>
      <area>S</area>
      <state>PR</state>
      <station>Foz do Iguaçu</station>
      <lat>-25.471197</lat>
      <lon>-54.549554</lon>
    </local>
    <measurements>
      <phasor>
        <pName>TENSAO_A</pName>
        <pType>Voltage</pType>
        <pPhase>A</pPhase>
        <modId>20829</modId>
        <angId>20830</angId>
      </phasor>
      <phasor>
        <pName>TENSAO_B</pName>
        <pType>Voltage</pType>
        <pPhase>B</pPhase>
        <modId>20827</modId>
        <angId>20828</angId>
      </phasor>
      <phasor>
        <pName>TENSAO_C</pName>
        <pType>Voltage</pType>
        <pPhase>C</pPhase>
        <modId>20825</modId>
        <angId>20826</angId>
      </phasor>
      <phasor>
        <pName>CORRENTE_A</pName>
        <pType>Current</pType>
        <pPhase>A</pPhase>
        <modId>20835</modId>
        <angId>20836</angId>
      </phasor>
      <phasor>
        <pName>CORRENTE_B</pName>
        <pType>Current</pType>
        <pPhase>B</pPhase>
        <modId>20833</modId>
        <angId>20834</angId>
      </phasor>
      <phasor>
        <pName>CORRENTE_C</pName>
        <pType>Current</pType>
        <pPhase>C</pPhase>
        <modId>20831</modId>
        <angId>20832</angId>
      </phasor>
      <freq>
        <fName>FREQUENCIA</fName>
        <fId>20822</fId>
      </freq>
      <dFreq>
        <dfName>DFREQ</dfName>
        <dfId>20823</dfId>
      </dFreq>
    </measurements>
  </pmu>
  <pmu>
    <idName>CV STF6 500 P4 TR8 VAO</idName>
    <fullName>CV STF6 500 P4 TR8 VAO</fullName>
    <voltLevel>500000</voltLevel>
    <local>
      <area>S</area>
      <state>PR</state>
      <station>Foz do Iguaçu</station>
      <lat>-25.471197</lat>
      <lon>-54.549554</lon>
    </local>
    <measurements>
      <phasor>
        <pName>TENSAO_A</pName>
        <pType>Voltage</pType>
        <pPhase>A</pPhase>
        <modId>20931</modId>
        <angId>20932</angId>
      </phasor>
      <phasor>
        <pName>TENSAO_B</pName>
        <pType>Voltage</pType>
        <pPhase>B</pPhase>
        <modId>20929</modId>
        <angId>20930</angId>
      </phasor>
      <phasor>
        <pName>TENSAO_C</pName>
        <pType>Voltage</pType>
        <pPhase>C</pPhase>
        <modId>20927</modId>
        <angId>20928</angId>
      </phasor>
      <phasor>
        <pName>CORRENTE_A</pName>
        <pType>Current</pType>
        <pPhase>A</pPhase>
        <modId>20937</modId>
        <angId>20938</angId>
      </phasor>
      <phasor>
        <pName>CORRENTE_B</pName>
        <pType>Current</pType>
        <pPhase>B</pPhase>
        <modId>20935</modId>
        <angId>20936</angId>
      </phasor>
      <phasor>
        <pName>CORRENTE_C</pName>
        <pType>Current</pType>
        <pPhase>C</pPhase>
        <modId>20933</modId>
        <angId>20934</angId>
      </phasor>
      <freq>
        <fName>FREQUENCIA</fName>
        <fId>20924</fId>
      </freq>
      <dFreq>
        <dfName>DFREQ</dfName>
        <dfId>20925</dfId>
      </dFreq>
    </measurements>
  </pmu>
  <pmu>
    <idName>CV STF6 500 P1 TR1 Y-D SEC</idName>
    <fullName>CV STF6 500 P1 TR1 Y-D SEC</fullName>
    <voltLevel>500000</voltLevel>
    <local>
      <area>S</area>
      <state>PR</state>
      <station>Foz do Iguaçu</station>
      <lat>-25.471197</lat>
      <lon>-54.549554</lon>
    </local>
    <measurements>
      <phasor>
        <pName>CORRENTE_A</pName>
        <pType>Current</pType>
        <pPhase>A</pPhase>
        <modId>20139</modId>
        <angId>20140</angId>
      </phasor>
      <phasor>
        <pName>CORRENTE_B</pName>
        <pType>Current</pType>
        <pPhase>B</pPhase>
        <modId>20137</modId>
        <angId>20138</angId>
      </phasor>
      <phasor>
        <pName>CORRENTE_C</pName>
        <pType>Current</pType>
        <pPhase>C</pPhase>
        <modId>20135</modId>
        <angId>20136</angId>
      </phasor>
      <freq>
        <fName>FREQUENCIA</fName>
        <fId>20132</fId>
      </freq>
      <dFreq>
        <dfName>DFREQ</dfName>
        <dfId>20133</dfId>
      </dFreq>
    </measurements>
  </pmu>
  <pmu>
    <idName>CV STF6 500 P1 TR1 Y-Y SEC</idName>
    <fullName>CV STF6 500 P1 TR1 Y-Y SEC</fullName>
    <voltLevel>500000</voltLevel>
    <local>
      <area>S</area>
      <state>PR</state>
      <station>Foz do Iguaçu</station>
      <lat>-25.471197</lat>
      <lon>-54.549554</lon>
    </local>
    <measurements>
      <phasor>
        <pName>CORRENTE_A</pName>
        <pType>Current</pType>
        <pPhase>A</pPhase>
        <modId>20149</modId>
        <angId>20150</angId>
      </phasor>
      <phasor>
        <pName>CORRENTE_B</pName>
        <pType>Current</pType>
        <pPhase>B</pPhase>
        <modId>20147</modId>
        <angId>20148</angId>
      </phasor>
      <phasor>
        <pName>CORRENTE_C</pName>
        <pType>Current</pType>
        <pPhase>C</pPhase>
        <modId>20145</modId>
        <angId>20146</angId>
      </phasor>
      <freq>
        <fName>FREQUENCIA</fName>
        <fId>20142</fId>
      </freq>
      <dFreq>
        <dfName>DFREQ</dfName>
        <dfId>20143</dfId>
      </dFreq>
    </measurements>
  </pmu>
  <pmu>
    <idName>CV STF6 500 P1 TR1 PRI</idName>
    <fullName>CV STF6 500 P1 TR1 PRI</fullName>
    <voltLevel>500000</voltLevel>
    <local>
      <area>S</area>
      <state>PR</state>
      <station>Foz do Iguaçu</station>
      <lat>-25.471197</lat>
      <lon>-54.549554</lon>
    </local>
    <measurements>
      <phasor>
        <pName>TENSAO_A</pName>
        <pType>Voltage</pType>
        <pPhase>A</pPhase>
        <modId>20175</modId>
        <angId>20176</angId>
      </phasor>
      <phasor>
        <pName>TENSAO_B</pName>
        <pType>Voltage</pType>
        <pPhase>B</pPhase>
        <modId>20173</modId>
        <angId>20174</angId>
      </phasor>
      <phasor>
        <pName>TENSAO_C</pName>
        <pType>Voltage</pType>
        <pPhase>C</pPhase>
        <modId>20171</modId>
        <angId>20172</angId>
      </phasor>
      <phasor>
        <pName>CORRENTE_A</pName>
        <pType>Current</pType>
        <pPhase>A</pPhase>
        <modId>20162</modId>
        <angId>20163</angId>
      </phasor>
      <phasor>
        <pName>CORRENTE_B</pName>
        <pType>Current</pType>
        <pPhase>B</pPhase>
        <modId>20160</modId>
        <angId>20161</angId>
      </phasor>
      <phasor>
        <pName>CORRENTE_C</pName>
        <pType>Current</pType>
        <pPhase>C</pPhase>
        <modId>20158</modId>
        <angId>20159</angId>
      </phasor>
      <freq>
        <fName>FREQUENCIA</fName>
        <fId>20155</fId>
      </freq>
      <dFreq>
        <dfName>DFREQ</dfName>
        <dfId>20156</dfId>
      </dFreq>
    </measurements>
  </pmu>
  <pmu>
    <idName>CV STF6 500 P1 TR3 Y-D SEC</idName>
    <fullName>CV STF6 500 P1 TR3 Y-D SEC</fullName>
    <voltLevel>500000</voltLevel>
    <local>
      <area>S</area>
      <state>PR</state>
      <station>Foz do Iguaçu</station>
      <lat>-25.471197</lat>
      <lon>-54.549554</lon>
    </local>
    <measurements>
      <phasor>
        <pName>CORRENTE_A</pName>
        <pType>Current</pType>
        <pPhase>A</pPhase>
        <modId>20241</modId>
        <angId>20242</angId>
      </phasor>
      <phasor>
        <pName>CORRENTE_B</pName>
        <pType>Current</pType>
        <pPhase>B</pPhase>
        <modId>20239</modId>
        <angId>20240</angId>
      </phasor>
      <phasor>
        <pName>CORRENTE_C</pName>
        <pType>Current</pType>
        <pPhase>C</pPhase>
        <modId>20237</modId>
        <angId>20238</angId>
      </phasor>
      <freq>
        <fName>FREQUENCIA</fName>
        <fId>20234</fId>
      </freq>
      <dFreq>
        <dfName>DFREQ</dfName>
        <dfId>20235</dfId>
      </dFreq>
    </measurements>
  </pmu>
  <pmu>
    <idName>CV STF6 500 P1 TR3 Y-Y SEC</idName>
    <fullName>CV STF6 500 P1 TR3 Y-Y SEC</fullName>
    <voltLevel>500000</voltLevel>
    <local>
      <area>S</area>
      <state>PR</state>
      <station>Foz do Iguaçu</station>
      <lat>-25.471197</lat>
      <lon>-54.549554</lon>
    </local>
    <measurements>
      <phasor>
        <pName>CORRENTE_A</pName>
        <pType>Current</pType>
        <pPhase>A</pPhase>
        <modId>20251</modId>
        <angId>20252</angId>
      </phasor>
      <phasor>
        <pName>CORRENTE_B</pName>
        <pType>Current</pType>
        <pPhase>B</pPhase>
        <modId>20249</modId>
        <angId>20250</angId>
      </phasor>
      <phasor>
        <pName>CORRENTE_C</pName>
        <pType>Current</pType>
        <pPhase>C</pPhase>
        <modId>20247</modId>
        <angId>20248</angId>
      </phasor>
      <freq>
        <fName>FREQUENCIA</fName>
        <fId>20244</fId>
      </freq>
      <dFreq>
        <dfName>DFREQ</dfName>
        <dfId>20245</dfId>
      </dFreq>
    </measurements>
  </pmu>
  <pmu>
    <idName>CV STF6 500 P1 TR3 PRI</idName>
    <fullName>CV STF6 500 P1 TR3 PRI</fullName>
    <voltLevel>500000</voltLevel>
    <local>
      <area>S</area>
      <state>PR</state>
      <station>Foz do Iguaçu</station>
      <lat>-25.471197</lat>
      <lon>-54.549554</lon>
    </local>
    <measurements>
	  <phasor>
        <pName>TENSAO_A</pName>
        <pType>Voltage</pType>
        <pPhase>A</pPhase>
        <modId>20277</modId>
        <angId>20278</angId>
      </phasor>
      <phasor>
        <pName>TENSAO_B</pName>
        <pType>Voltage</pType>
        <pPhase>B</pPhase>
        <modId>20275</modId>
        <angId>20276</angId>
      </phasor>
      <phasor>
        <pName>TENSAO_C</pName>
        <pType>Voltage</pType>
        <pPhase>C</pPhase>
        <modId>20273</modId>
        <angId>20274</angId>
      </phasor>
      <phasor>
        <pName>CORRENTE_A</pName>
        <pType>Current</pType>
        <pPhase>A</pPhase>
        <modId>20264</modId>
        <angId>20265</angId>
      </phasor>
      <phasor>
        <pName>CORRENTE_B</pName>
        <pType>Current</pType>
        <pPhase>B</pPhase>
        <modId>20262</modId>
        <angId>20263</angId>
      </phasor>
      <phasor>
        <pName>CORRENTE_C</pName>
        <pType>Current</pType>
        <pPhase>C</pPhase>
        <modId>20260</modId>
        <angId>20261</angId>
      </phasor>
      <freq>
        <fName>FREQUENCIA</fName>
        <fId>20257</fId>
      </freq>
      <dFreq>
        <dfName>DFREQ</dfName>
        <dfId>20258</dfId>
      </dFreq>
    </measurements>
  </pmu>
  <pmu>
    <idName>CV STF6 500 P2 TR2 Y-D SEC</idName>
    <fullName>CV STF6 500 P2 TR2 Y-D SEC</fullName>
    <voltLevel>500000</voltLevel>
    <local>
      <area>S</area>
      <state>PR</state>
      <station>Foz do Iguaçu</station>
      <lat>-25.471197</lat>
      <lon>-54.549554</lon>
    </local>
    <measurements>
      <phasor>
        <pName>CORRENTE_A</pName>
        <pType>Current</pType>
        <pPhase>A</pPhase>
        <modId>20343</modId>
        <angId>20344</angId>
      </phasor>
      <phasor>
        <pName>CORRENTE_B</pName>
        <pType>Current</pType>
        <pPhase>B</pPhase>
        <modId>20341</modId>
        <angId>20342</angId>
      </phasor>
      <phasor>
        <pName>CORRENTE_C</pName>
        <pType>Current</pType>
        <pPhase>C</pPhase>
        <modId>20339</modId>
        <angId>20340</angId>
      </phasor>
      <freq>
        <fName>FREQUENCIA</fName>
        <fId>20336</fId>
      </freq>
      <dFreq>
        <dfName>DFREQ</dfName>
        <dfId>20337</dfId>
      </dFreq>
    </measurements>
  </pmu>
  <pmu>
    <idName>CV STF6 500 P2 TR2 Y-Y SEC</idName>
    <fullName>CV STF6 500 P2 TR2 Y-Y SEC</fullName>
    <voltLevel>500000</voltLevel>
    <local>
      <area>S</area>
      <state>PR</state>
      <station>Foz do Iguaçu</station>
      <lat>-25.471197</lat>
      <lon>-54.549554</lon>
    </local>
    <measurements>
      <phasor>
        <pName>CORRENTE_A</pName>
        <pType>Current</pType>
        <pPhase>A</pPhase>
        <modId>20353</modId>
        <angId>20354</angId>
      </phasor>
      <phasor>
        <pName>CORRENTE_B</pName>
        <pType>Current</pType>
        <pPhase>B</pPhase>
        <modId>20351</modId>
        <angId>20352</angId>
      </phasor>
      <phasor>
        <pName>CORRENTE_C</pName>
        <pType>Current</pType>
        <pPhase>C</pPhase>
        <modId>20349</modId>
        <angId>20350</angId>
      </phasor>
      <freq>
        <fName>FREQUENCIA</fName>
        <fId>20346</fId>
      </freq>
      <dFreq>
        <dfName>DFREQ</dfName>
        <dfId>20347</dfId>
      </dFreq>
    </measurements>
  </pmu>
  <pmu>
    <idName>CV STF6 500 P2 TR2 PRI</idName>
    <fullName>CV STF6 500 P2 TR2 PRI</fullName>
    <voltLevel>500000</voltLevel>
    <local>
      <area>S</area>
      <state>PR</state>
      <station>Foz do Iguaçu</station>
      <lat>-25.471197</lat>
      <lon>-54.549554</lon>
    </local>
    <measurements>
      <phasor>
        <pName>TENSAO_A</pName>
        <pType>Voltage</pType>
        <pPhase>A</pPhase>
        <modId>20379</modId>
        <angId>20380</angId>
      </phasor>
      <phasor>
        <pName>TENSAO_B</pName>
        <pType>Voltage</pType>
        <pPhase>B</pPhase>
        <modId>20377</modId>
        <angId>20378</angId>
      </phasor>
      <phasor>
        <pName>TENSAO_C</pName>
        <pType>Voltage</pType>
        <pPhase>C</pPhase>
        <modId>20375</modId>
        <angId>20376</angId>
      </phasor>
      <phasor>
        <pName>CORRENTE_A</pName>
        <pType>Current</pType>
        <pPhase>A</pPhase>
        <modId>20366</modId>
        <angId>20367</angId>
      </phasor>
      <phasor>
        <pName>CORRENTE_B</pName>
        <pType>Current</pType>
        <pPhase>B</pPhase>
        <modId>20364</modId>
        <angId>20365</angId>
      </phasor>
      <phasor>
        <pName>CORRENTE_C</pName>
        <pType>Current</pType>
        <pPhase>C</pPhase>
        <modId>20362</modId>
        <angId>20363</angId>
      </phasor>
      <freq>
        <fName>FREQUENCIA</fName>
        <fId>20359</fId>
      </freq>
      <dFreq>
        <dfName>DFREQ</dfName>
        <dfId>20360</dfId>
      </dFreq>
    </measurements>
  </pmu>
  <pmu>
    <idName>CV STF6 500 P2 TR4 Y-D SEC</idName>
    <fullName>CV STF6 500 P2 TR4 Y-D SEC</fullName>
    <voltLevel>500000</voltLevel>
    <local>
      <area>S</area>
      <state>PR</state>
      <station>Foz do Iguaçu</station>
      <lat>-25.471197</lat>
      <lon>-54.549554</lon>
    </local>
    <measurements>
      <phasor>
        <pName>CORRENTE_A</pName>
        <pType>Current</pType>
        <pPhase>A</pPhase>
        <modId>20445</modId>
        <angId>20446</angId>
      </phasor>
      <phasor>
        <pName>CORRENTE_B</pName>
        <pType>Current</pType>
        <pPhase>B</pPhase>
        <modId>20443</modId>
        <angId>20444</angId>
      </phasor>
      <phasor>
        <pName>CORRENTE_C</pName>
        <pType>Current</pType>
        <pPhase>C</pPhase>
        <modId>20441</modId>
        <angId>20442</angId>
      </phasor>
      <freq>
        <fName>FREQUENCIA</fName>
        <fId>20438</fId>
      </freq>
      <dFreq>
        <dfName>DFREQ</dfName>
        <dfId>20439</dfId>
      </dFreq>
    </measurements>
  </pmu>
  <pmu>
    <idName>CV STF6 500 P2 TR4 Y-Y SEC</idName>
    <fullName>CV STF6 500 P2 TR4 Y-Y SEC</fullName>
    <voltLevel>500000</voltLevel>
    <local>
      <area>S</area>
      <state>PR</state>
      <station>Foz do Iguaçu</station>
      <lat>-25.471197</lat>
      <lon>-54.549554</lon>
    </local>
    <measurements>
      <phasor>
        <pName>CORRENTE_A</pName>
        <pType>Current</pType>
        <pPhase>A</pPhase>
        <modId>20455</modId>
        <angId>20456</angId>
      </phasor>
      <phasor>
        <pName>CORRENTE_B</pName>
        <pType>Current</pType>
        <pPhase>B</pPhase>
        <modId>20453</modId>
        <angId>20454</angId>
      </phasor>
      <phasor>
        <pName>CORRENTE_C</pName>
        <pType>Current</pType>
        <pPhase>C</pPhase>
        <modId>20451</modId>
        <angId>20452</angId>
      </phasor>
      <freq>
        <fName>FREQUENCIA</fName>
        <fId>20448</fId>
      </freq>
      <dFreq>
        <dfName>DFREQ</dfName>
        <dfId>20449</dfId>
      </dFreq>
    </measurements>
  </pmu>
  <pmu>
    <idName>CV STF6 500 P2 TR4 PRI</idName>
    <fullName>CV STF6 500 P2 TR4 PRI</fullName>
    <voltLevel>500000</voltLevel>
    <local>
      <area>S</area>
      <state>PR</state>
      <station>Foz do Iguaçu</station>
      <lat>-25.471197</lat>
      <lon>-54.549554</lon>
    </local>
    <measurements>
      <phasor>
        <pName>TENSAO_A</pName>
        <pType>Voltage</pType>
        <pPhase>A</pPhase>
        <modId>20481</modId>
        <angId>20482</angId>
      </phasor>
      <phasor>
        <pName>TENSAO_B</pName>
        <pType>Voltage</pType>
        <pPhase>B</pPhase>
        <modId>20479</modId>
        <angId>20480</angId>
      </phasor>
      <phasor>
        <pName>TENSAO_C</pName>
        <pType>Voltage</pType>
        <pPhase>C</pPhase>
        <modId>20477</modId>
        <angId>20478</angId>
      </phasor>
      <phasor>
        <pName>CORRENTE_A</pName>
        <pType>Current</pType>
        <pPhase>A</pPhase>
        <modId>20468</modId>
        <angId>20469</angId>
      </phasor>
      <phasor>
        <pName>CORRENTE_B</pName>
        <pType>Current</pType>
        <pPhase>B</pPhase>
        <modId>20466</modId>
        <angId>20467</angId>
      </phasor>
      <phasor>
        <pName>CORRENTE_C</pName>
        <pType>Current</pType>
        <pPhase>C</pPhase>
        <modId>20464</modId>
        <angId>20465</angId>
      </phasor>
      <freq>
        <fName>FREQUENCIA</fName>
        <fId>20461</fId>
      </freq>
      <dFreq>
        <dfName>DFREQ</dfName>
        <dfId>20462</dfId>
      </dFreq>
    </measurements>
  </pmu>
  <pmu>
    <idName>CV STF6 500 P3 TR5 Y-D SEC</idName>
    <fullName>CV STF6 500 P3 TR5 Y-D SEC</fullName>
    <voltLevel>500000</voltLevel>
    <local>
      <area>S</area>
      <state>PR</state>
      <station>Foz do Iguaçu</station>
      <lat>-25.471197</lat>
      <lon>-54.549554</lon>
    </local>
    <measurements>
      <phasor>
        <pName>CORRENTE_A</pName>
        <pType>Current</pType>
        <pPhase>A</pPhase>
        <modId>20547</modId>
        <angId>20548</angId>
      </phasor>
      <phasor>
        <pName>CORRENTE_B</pName>
        <pType>Current</pType>
        <pPhase>B</pPhase>
        <modId>20545</modId>
        <angId>20546</angId>
      </phasor>
      <phasor>
        <pName>CORRENTE_C</pName>
        <pType>Current</pType>
        <pPhase>C</pPhase>
        <modId>20543</modId>
        <angId>20544</angId>
      </phasor>
      <freq>
        <fName>FREQUENCIA</fName>
        <fId>20540</fId>
      </freq>
      <dFreq>
        <dfName>DFREQ</dfName>
        <dfId>20541</dfId>
      </dFreq>
    </measurements>
  </pmu>
  <pmu>
    <idName>CV STF6 500 P3 TR5 Y-Y SEC</idName>
    <fullName>CV STF6 500 P3 TR5 Y-Y SEC</fullName>
    <voltLevel>500000</voltLevel>
    <local>
      <area>S</area>
      <state>PR</state>
      <station>Foz do Iguaçu</station>
      <lat>-25.471197</lat>
      <lon>-54.549554</lon>
    </local>
    <measurements>
      <phasor>
        <pName>CORRENTE_A</pName>
        <pType>Current</pType>
        <pPhase>A</pPhase>
        <modId>20557</modId>
        <angId>20558</angId>
      </phasor>
      <phasor>
        <pName>CORRENTE_B</pName>
        <pType>Current</pType>
        <pPhase>B</pPhase>
        <modId>20555</modId>
        <angId>20556</angId>
      </phasor>
      <phasor>
        <pName>CORRENTE_C</pName>
        <pType>Current</pType>
        <pPhase>C</pPhase>
        <modId>20553</modId>
        <angId>20554</angId>
      </phasor>
      <freq>
        <fName>FREQUENCIA</fName>
        <fId>20550</fId>
      </freq>
      <dFreq>
        <dfName>DFREQ</dfName>
        <dfId>20551</dfId>
      </dFreq>
    </measurements>
  </pmu>
  <pmu>
    <idName>CV STF6 500 P3 TR5 PRI</idName>
    <fullName>CV STF6 500 P3 TR5 PRI</fullName>
    <voltLevel>500000</voltLevel>
    <local>
      <area>S</area>
      <state>PR</state>
      <station>Foz do Iguaçu</station>
      <lat>-25.471197</lat>
      <lon>-54.549554</lon>
    </local>
    <measurements>
      <phasor>
        <pName>TENSAO_A</pName>
        <pType>Voltage</pType>
        <pPhase>A</pPhase>
        <modId>20583</modId>
        <angId>20584</angId>
      </phasor>
      <phasor>
        <pName>TENSAO_B</pName>
        <pType>Voltage</pType>
        <pPhase>B</pPhase>
        <modId>20581</modId>
        <angId>20582</angId>
      </phasor>
      <phasor>
        <pName>TENSAO_C</pName>
        <pType>Voltage</pType>
        <pPhase>C</pPhase>
        <modId>20579</modId>
        <angId>20580</angId>
      </phasor>
      <phasor>
        <pName>CORRENTE_A</pName>
        <pType>Current</pType>
        <pPhase>A</pPhase>
        <modId>20570</modId>
        <angId>20571</angId>
      </phasor>
      <phasor>
        <pName>CORRENTE_B</pName>
        <pType>Current</pType>
        <pPhase>B</pPhase>
        <modId>20568</modId>
        <angId>20569</angId>
      </phasor>
      <phasor>
        <pName>CORRENTE_C</pName>
        <pType>Current</pType>
        <pPhase>C</pPhase>
        <modId>20566</modId>
        <angId>20567</angId>
      </phasor>
      <freq>
        <fName>FREQUENCIA</fName>
        <fId>20563</fId>
      </freq>
      <dFreq>
        <dfName>DFREQ</dfName>
        <dfId>20564</dfId>
      </dFreq>
    </measurements>
  </pmu>
  <pmu>
    <idName>CV STF6 500 P3 TR7 Y-D SEC</idName>
    <fullName>CV STF6 500 P3 TR7 Y-D SEC</fullName>
    <voltLevel>500000</voltLevel>
    <local>
      <area>S</area>
      <state>PR</state>
      <station>Foz do Iguaçu</station>
      <lat>-25.471197</lat>
      <lon>-54.549554</lon>
    </local>
    <measurements>
      <phasor>
        <pName>CORRENTE_A</pName>
        <pType>Current</pType>
        <pPhase>A</pPhase>
        <modId>20649</modId>
        <angId>20650</angId>
      </phasor>
      <phasor>
        <pName>CORRENTE_B</pName>
        <pType>Current</pType>
        <pPhase>B</pPhase>
        <modId>20647</modId>
        <angId>20648</angId>
      </phasor>
      <phasor>
        <pName>CORRENTE_C</pName>
        <pType>Current</pType>
        <pPhase>C</pPhase>
        <modId>20645</modId>
        <angId>20646</angId>
      </phasor>
      <freq>
        <fName>FREQUENCIA</fName>
        <fId>20642</fId>
      </freq>
      <dFreq>
        <dfName>DFREQ</dfName>
        <dfId>20643</dfId>
      </dFreq>
    </measurements>
  </pmu>
  <pmu>
    <idName>CV STF6 500 P3 TR7 Y-Y SEC</idName>
    <fullName>CV STF6 500 P3 TR7 Y-Y SEC</fullName>
    <voltLevel>500000</voltLevel>
    <local>
      <area>S</area>
      <state>PR</state>
      <station>Foz do Iguaçu</station>
      <lat>-25.471197</lat>
      <lon>-54.549554</lon>
    </local>
    <measurements>
      <phasor>
        <pName>CORRENTE_A</pName>
        <pType>Current</pType>
        <pPhase>A</pPhase>
        <modId>20659</modId>
        <angId>20660</angId>
      </phasor>
      <phasor>
        <pName>CORRENTE_B</pName>
        <pType>Current</pType>
        <pPhase>B</pPhase>
        <modId>20657</modId>
        <angId>20658</angId>
      </phasor>
      <phasor>
        <pName>CORRENTE_C</pName>
        <pType>Current</pType>
        <pPhase>C</pPhase>
        <modId>20655</modId>
        <angId>20656</angId>
      </phasor>
      <freq>
        <fName>FREQUENCIA</fName>
        <fId>20652</fId>
      </freq>
      <dFreq>
        <dfName>DFREQ</dfName>
        <dfId>20653</dfId>
      </dFreq>
    </measurements>
  </pmu>
  <pmu>
    <idName>CV STF6 500 P3 TR7 PRI</idName>
    <fullName>CV STF6 500 P3 TR7 PRI</fullName>
    <voltLevel>500000</voltLevel>
    <local>
      <area>S</area>
      <state>PR</state>
      <station>Foz do Iguaçu</station>
      <lat>-25.471197</lat>
      <lon>-54.549554</lon>
    </local>
    <measurements>
      <phasor>
        <pName>TENSAO_A</pName>
        <pType>Voltage</pType>
        <pPhase>A</pPhase>
        <modId>20685</modId>
        <angId>20686</angId>
      </phasor>
      <phasor>
        <pName>TENSAO_B</pName>
        <pType>Voltage</pType>
        <pPhase>B</pPhase>
        <modId>20683</modId>
        <angId>20684</angId>
      </phasor>
      <phasor>
        <pName>TENSAO_C</pName>
        <pType>Voltage</pType>
        <pPhase>C</pPhase>
        <modId>20681</modId>
        <angId>20682</angId>
      </phasor>
      <phasor>
        <pName>CORRENTE_A</pName>
        <pType>Current</pType>
        <pPhase>A</pPhase>
        <modId>20672</modId>
        <angId>20673</angId>
      </phasor>
      <phasor>
        <pName>CORRENTE_B</pName>
        <pType>Current</pType>
        <pPhase>B</pPhase>
        <modId>20670</modId>
        <angId>20671</angId>
      </phasor>
      <phasor>
        <pName>CORRENTE_C</pName>
        <pType>Current</pType>
        <pPhase>C</pPhase>
        <modId>20668</modId>
        <angId>20669</angId>
      </phasor>
      <freq>
        <fName>FREQUENCIA</fName>
        <fId>20665</fId>
      </freq>
      <dFreq>
        <dfName>DFREQ</dfName>
        <dfId>20666</dfId>
      </dFreq>
    </measurements>
  </pmu>
  <pmu>
    <idName>CV STF6 500 P4 TR6 Y-D SEC</idName>
    <fullName>CV STF6 500 P4 TR6 Y-D SEC</fullName>
    <voltLevel>500000</voltLevel>
    <local>
      <area>S</area>
      <state>PR</state>
      <station>Foz do Iguaçu</station>
      <lat>-25.471197</lat>
      <lon>-54.549554</lon>
    </local>
    <measurements>
      <phasor>
        <pName>CORRENTE_A</pName>
        <pType>Current</pType>
        <pPhase>A</pPhase>
        <modId>20751</modId>
        <angId>20752</angId>
      </phasor>
      <phasor>
        <pName>CORRENTE_B</pName>
        <pType>Current</pType>
        <pPhase>B</pPhase>
        <modId>20749</modId>
        <angId>20750</angId>
      </phasor>
      <phasor>
        <pName>CORRENTE_C</pName>
        <pType>Current</pType>
        <pPhase>C</pPhase>
        <modId>20747</modId>
        <angId>20748</angId>
      </phasor>
      <freq>
        <fName>FREQUENCIA</fName>
        <fId>20744</fId>
      </freq>
      <dFreq>
        <dfName>DFREQ</dfName>
        <dfId>20745</dfId>
      </dFreq>
    </measurements>
  </pmu>
  <pmu>
    <idName>CV STF6 500 P4 TR6 Y-Y SEC</idName>
    <fullName>CV STF6 500 P4 TR6 Y-Y SEC</fullName>
    <voltLevel>500000</voltLevel>
    <local>
      <area>S</area>
      <state>PR</state>
      <station>Foz do Iguaçu</station>
      <lat>-25.471197</lat>
      <lon>-54.549554</lon>
    </local>
    <measurements>
      <phasor>
        <pName>CORRENTE_A</pName>
        <pType>Current</pType>
        <pPhase>A</pPhase>
        <modId>20761</modId>
        <angId>20762</angId>
      </phasor>
      <phasor>
        <pName>CORRENTE_B</pName>
        <pType>Current</pType>
        <pPhase>B</pPhase>
        <modId>20759</modId>
        <angId>20760</angId>
      </phasor>
      <phasor>
        <pName>CORRENTE_C</pName>
        <pType>Current</pType>
        <pPhase>C</pPhase>
        <modId>20757</modId>
        <angId>20758</angId>
      </phasor>
      <freq>
        <fName>FREQUENCIA</fName>
        <fId>20754</fId>
      </freq>
      <dFreq>
        <dfName>DFREQ</dfName>
        <dfId>20755</dfId>
      </dFreq>
    </measurements>
  </pmu>
  <pmu>
    <idName>CV STF6 500 P4 TR6 PRI</idName>
    <fullName>CV STF6 500 P4 TR6 PRI</fullName>
    <voltLevel>500000</voltLevel>
    <local>
      <area>S</area>
      <state>PR</state>
      <station>Foz do Iguaçu</station>
      <lat>-25.471197</lat>
      <lon>-54.549554</lon>
    </local>
    <measurements>
      <phasor>
        <pName>TENSAO_A</pName>
        <pType>Voltage</pType>
        <pPhase>A</pPhase>
        <modId>20787</modId>
        <angId>20788</angId>
      </phasor>
      <phasor>
        <pName>TENSAO_B</pName>
        <pType>Voltage</pType>
        <pPhase>B</pPhase>
        <modId>20785</modId>
        <angId>20786</angId>
      </phasor>
      <phasor>
        <pName>TENSAO_C</pName>
        <pType>Voltage</pType>
        <pPhase>C</pPhase>
        <modId>20783</modId>
        <angId>20784</angId>
      </phasor>
      <phasor>
        <pName>CORRENTE_A</pName>
        <pType>Current</pType>
        <pPhase>A</pPhase>
        <modId>20774</modId>
        <angId>20775</angId>
      </phasor>
      <phasor>
        <pName>CORRENTE_B</pName>
        <pType>Current</pType>
        <pPhase>B</pPhase>
        <modId>20772</modId>
        <angId>20773</angId>
      </phasor>
      <phasor>
        <pName>CORRENTE_C</pName>
        <pType>Current</pType>
        <pPhase>C</pPhase>
        <modId>20770</modId>
        <angId>20771</angId>
      </phasor>
      <freq>
        <fName>FREQUENCIA</fName>
        <fId>20767</fId>
      </freq>
      <dFreq>
        <dfName>DFREQ</dfName>
        <dfId>20768</dfId>
      </dFreq>
    </measurements>
  </pmu>
  <pmu>
    <idName>CV STF6 500 P4 TR8 Y-D SEC</idName>
    <fullName>CV STF6 500 P4 TR8 Y-D SEC</fullName>
    <voltLevel>500000</voltLevel>
    <local>
      <area>S</area>
      <state>PR</state>
      <station>Foz do Iguaçu</station>
      <lat>-25.471197</lat>
      <lon>-54.549554</lon>
    </local>
    <measurements>
      <phasor>
        <pName>CORRENTE_A</pName>
        <pType>Current</pType>
        <pPhase>A</pPhase>
        <modId>20853</modId>
        <angId>20854</angId>
      </phasor>
      <phasor>
        <pName>CORRENTE_B</pName>
        <pType>Current</pType>
        <pPhase>B</pPhase>
        <modId>20851</modId>
        <angId>20852</angId>
      </phasor>
      <phasor>
        <pName>CORRENTE_C</pName>
        <pType>Current</pType>
        <pPhase>C</pPhase>
        <modId>20849</modId>
        <angId>20850</angId>
      </phasor>
      <freq>
        <fName>FREQUENCIA</fName>
        <fId>20846</fId>
      </freq>
      <dFreq>
        <dfName>DFREQ</dfName>
        <dfId>20847</dfId>
      </dFreq>
    </measurements>
  </pmu>
  <pmu>
    <idName>CV STF6 500 P4 TR8 Y-Y SEC</idName>
    <fullName>CV STF6 500 P4 TR8 Y-Y SEC</fullName>
    <voltLevel>500000</voltLevel>
    <local>
      <area>S</area>
      <state>PR</state>
      <station>Foz do Iguaçu</station>
      <lat>-25.471197</lat>
      <lon>-54.549554</lon>
    </local>
    <measurements>
      <phasor>
        <pName>CORRENTE_A</pName>
        <pType>Current</pType>
        <pPhase>A</pPhase>
        <modId>20863</modId>
        <angId>20864</angId>
      </phasor>
      <phasor>
        <pName>CORRENTE_B</pName>
        <pType>Current</pType>
        <pPhase>B</pPhase>
        <modId>20861</modId>
        <angId>20862</angId>
      </phasor>
      <phasor>
        <pName>CORRENTE_C</pName>
        <pType>Current</pType>
        <pPhase>C</pPhase>
        <modId>20859</modId>
        <angId>20860</angId>
      </phasor>
      <freq>
        <fName>FREQUENCIA</fName>
        <fId>20856</fId>
      </freq>
      <dFreq>
        <dfName>DFREQ</dfName>
        <dfId>20857</dfId>
      </dFreq>
    </measurements>
  </pmu>
  <pmu>
    <idName>CV STF6 500 P4 TR8 PRI</idName>
    <fullName>CV STF6 500 P4 TR8 PRI</fullName>
    <voltLevel>500000</voltLevel>
    <local>
      <area>S</area>
      <state>PR</state>
      <station>Foz do Iguaçu</station>
      <lat>-25.471197</lat>
      <lon>-54.549554</lon>
    </local>
    <measurements>
      <phasor>
        <pName>TENSAO_A</pName>
        <pType>Voltage</pType>
        <pPhase>A</pPhase>
        <modId>20889</modId>
        <angId>20890</angId>
      </phasor>
      <phasor>
        <pName>TENSAO_B</pName>
        <pType>Voltage</pType>
        <pPhase>B</pPhase>
        <modId>20887</modId>
        <angId>20888</angId>
      </phasor>
      <phasor>
        <pName>TENSAO_C</pName>
        <pType>Voltage</pType>
        <pPhase>C</pPhase>
        <modId>20885</modId>
        <angId>20886</angId>
      </phasor>
      <phasor>
        <pName>CORRENTE_A</pName>
        <pType>Current</pType>
        <pPhase>A</pPhase>
        <modId>20876</modId>
        <angId>20877</angId>
      </phasor>
      <phasor>
        <pName>CORRENTE_B</pName>
        <pType>Current</pType>
        <pPhase>B</pPhase>
        <modId>20874</modId>
        <angId>20875</angId>
      </phasor>
      <phasor>
        <pName>CORRENTE_C</pName>
        <pType>Current</pType>
        <pPhase>C</pPhase>
        <modId>20872</modId>
        <angId>20873</angId>
      </phasor>
      <freq>
        <fName>FREQUENCIA</fName>
        <fId>20869</fId>
      </freq>
      <dFreq>
        <dfName>DFREQ</dfName>
        <dfId>20870</dfId>
      </dFreq>
    </measurements>
  </pmu>
</smsf>